{"composition-api_useauth.md":"a738978f","composition-api_useuser.md":"888794c7","guide_auth-meta.md":"34374a66","guide_cookie.md":"4819ae4d","guide_drivers.md":"32003481","guide_getting-started.md":"49a2393a","guide_oauth2.md":"d2c00ee5","guide_plugins.md":"56a0a004","guide_requests.md":"cccb7503","guide_token.md":"8aafd158","index.md":"5bd29027","introduction.md":"2c2a8ec8","methods_impersonating.md":"45fa2ef5","methods_init.md":"d5b8a856","methods_overview.md":"fa0b44d9","methods_register-and-login.md":"7375073d","methods_user-data.md":"728b607a","methods_utils.md":"2c337c3c","options_core.md":"8dbbfd58","options_options-generate.md":"6aaaf98c"}
