{"composition-api_useauth.md":"a1e2a48b","composition-api_useuser.md":"428b6999","guide_auth-meta.md":"9e5f436d","guide_cookie.md":"58575934","guide_drivers.md":"f985052b","guide_getting-started.md":"1dfea833","guide_oauth2.md":"1da4d9a6","guide_plugins.md":"472f4300","guide_requests.md":"f0749b5e","guide_token.md":"f0c3562e","index.md":"63ba3020","introduction.md":"6da5c4f7","methods_impersonating.md":"ffba119b","methods_init.md":"42d98307","methods_overview.md":"0be64353","methods_register-and-login.md":"5f258e48","methods_user-data.md":"07531283","methods_utils.md":"0a5f0597","options_core.md":"d0553c83","options_options-generate.md":"6528a67b"}
